{
  "list": [
    {
      "src": "//cdn.cnbj0.fds.api.mi-img.com/b2c-mimall-media/7e98be403a5f4277adba84acaecb9c76.jpg?bg=6D96C7",
      "id": "1001",
      "title": "小米Note3 人脸解锁",
      "money": 2099
    },
    {
      "src": "//cdn.cnbj0.fds.api.mi-img.com/b2c-mimall-media/8e8f00d32ef069600bf047c05bb5abd6.jpg?bg=AEB9C9",
      "id": "1002",
      "title": "小米Max2 大屏大电量",
      "money": 1999
    },
    {
      "src": "//cdn.cnbj0.fds.api.mi-img.com/b2c-mimall-media/275b4b53477b55f38c9d9b7fdf4d913b.jpg?bg=684A46",
      "id": "1003",
      "title": "小米MIX2 全面屏2.0",
      "money": 2999
    },
    {
      "src": "//cdn.cnbj0.fds.api.mi-img.com/b2c-mimall-media/f2230cfe9ac3090ebd6d5d9c2a0fdec3.jpg?bg=827470",
      "id": "1004",
      "title": "小米电视4A 50英寸",
      "money": 2399
    }
  ]
}